odoo9_addon_stock_scanner_inventory-9.0.1.0.0.99.dev3-py2.7-nspkg.pth
odoo9_addon_stock_scanner_inventory-9.0.1.0.0.99.dev3.dist-info/METADATA
odoo9_addon_stock_scanner_inventory-9.0.1.0.0.99.dev3.dist-info/RECORD
odoo9_addon_stock_scanner_inventory-9.0.1.0.0.99.dev3.dist-info/WHEEL
odoo9_addon_stock_scanner_inventory-9.0.1.0.0.99.dev3.dist-info/namespace_packages.txt
odoo9_addon_stock_scanner_inventory-9.0.1.0.0.99.dev3.dist-info/top_level.txt
odoo_addons/stock_scanner_inventory/README.rst
odoo_addons/stock_scanner_inventory/__init__.py
odoo_addons/stock_scanner_inventory/__openerp__.py
odoo_addons/stock_scanner_inventory/data/Stock.scenario
odoo_addons/stock_scanner_inventory/data/Inventory/Inventory.scenario
odoo_addons/stock_scanner_inventory/data/Inventory/scanner_scenario_step_inventory_done.py
odoo_addons/stock_scanner_inventory/data/Inventory/scanner_scenario_step_inventory_end_confirm.py
odoo_addons/stock_scanner_inventory/data/Inventory/scanner_scenario_step_inventory_location_selection.py
odoo_addons/stock_scanner_inventory/data/Inventory/scanner_scenario_step_inventory_product_code.py
odoo_addons/stock_scanner_inventory/data/Inventory/scanner_scenario_step_inventory_product_quantity.py
odoo_addons/stock_scanner_inventory/data/Inventory/scanner_scenario_step_inventory_unknown_location.py
odoo_addons/stock_scanner_inventory/data/Inventory/scanner_scenario_step_inventory_unknown_product.py
odoo_addons/stock_scanner_inventory/i18n/stock_scanner_inventory.pot
odoo_addons/stock_scanner_inventory/images/scenario.png
odoo_addons/stock_scanner_inventory/static/description/icon.png
