Metadata-Version: 2.1
Name: odoo9-addon-stock-scanner-inventory
Version: 9.0.1.0.0.99.dev3
Summary: Stock Scanner Inventory
Home-page: https://odoo-community.org/
Author: SYLEAM,Odoo Community Association (OCA)
Author-email: support@odoo-community.org
License: AGPL-3
Platform: UNKNOWN
Classifier: Programming Language :: Python
Classifier: Framework :: Odoo
Classifier: License :: OSI Approved :: GNU Affero General Public License v3
Requires-Python: ~=2.7
Requires-Dist: odoo9-addon-stock-scanner
Requires-Dist: odoo (<9.1a,>=9.0a)
